MANIFEST.in
setup.cfg
setup.py
Products/__init__.py
Products.ATPhoto.egg-info/PKG-INFO
Products.ATPhoto.egg-info/SOURCES.txt
Products.ATPhoto.egg-info/dependency_links.txt
Products.ATPhoto.egg-info/entry_points.txt
Products.ATPhoto.egg-info/namespace_packages.txt
Products.ATPhoto.egg-info/not-zip-safe
Products.ATPhoto.egg-info/requires.txt
Products.ATPhoto.egg-info/top_level.txt
Products/ATPhoto/ATPhoto.py
Products/ATPhoto/ATPhotoAlbum.py
Products/ATPhoto/ATPhotoTransform.py
Products/ATPhoto/AppConfig.py
Products/ATPhoto/FlickrExportable.py
Products/ATPhoto/TODO.txt
Products/ATPhoto/__init__.py
Products/ATPhoto/adapters.py
Products/ATPhoto/browser.py
Products/ATPhoto/config.py
Products/ATPhoto/configure.zcml
Products/ATPhoto/exceptions.py
Products/ATPhoto/interfaces.py
Products/ATPhoto/refresh.txt
Products/ATPhoto/scalable.zcml
Products/ATPhoto/uploadr.py
Products/ATPhoto/version.txt
Products/ATPhoto/xmltramp.py
Products/ATPhoto/Extensions/AppInstall.py
Products/ATPhoto/Extensions/Install.py
Products/ATPhoto/Extensions/__init__.py
Products/ATPhoto/doc/AUTHORS.txt
Products/ATPhoto/doc/HISTORY.txt
Products/ATPhoto/doc/README.txt
Products/ATPhoto/doc/__init__.py
Products/ATPhoto/doc/testATContentTypeExifInterface.txt
Products/ATPhoto/i18n/ATPhoto-da.po
Products/ATPhoto/i18n/ATPhoto-pt-br.po
Products/ATPhoto/i18n/generated.pot
Products/ATPhoto/model/ATPhoto.zuml
Products/ATPhoto/skins/ATPhoto/atphoto.css.dtml
Products/ATPhoto/skins/ATPhoto/atphoto.js
Products/ATPhoto/skins/ATPhoto/atphotoListPhoto.cpy
Products/ATPhoto/skins/ATPhoto/atphoto_export.cpt
Products/ATPhoto/skins/ATPhoto/atphoto_infos.pt
Products/ATPhoto/skins/ATPhoto/atphoto_macros.pt
Products/ATPhoto/skins/ATPhoto/atphoto_transform.cpt
Products/ATPhoto/skins/ATPhoto/atphoto_transitions.js
Products/ATPhoto/skins/ATPhoto/atphoto_view.cpt
Products/ATPhoto/skins/ATPhoto/atphotoalbum.js
Products/ATPhoto/skins/ATPhoto/atphotoalbum_dom_view.cpt
Products/ATPhoto/skins/ATPhoto/atphotoalbum_export.cpt
Products/ATPhoto/skins/ATPhoto/atphotoalbum_import.cpt
Products/ATPhoto/skins/ATPhoto/atphotoalbum_listing.pt
Products/ATPhoto/skins/ATPhoto/atphotoalbum_slideshow.cpt
Products/ATPhoto/skins/ATPhoto/atphotoalbum_slideshow.cpt.metadata
Products/ATPhoto/skins/ATPhoto/atphotoalbum_view.cpt
Products/ATPhoto/skins/ATPhoto/atslideshow.js
