Metadata-Version: 1.0
Name: Products.ATPhoto
Version: 1.0
Summary: ATPhoto is a product to manage photos in your Plone site
Home-page: https://svn.plone.org/svn/collective/Products.ATPhoto
Author: Russ Ferriday
Author-email: russ@topia.com
License: GPL
Keywords: plone ATPhoto
Platform: UNKNOWN
Classifier: Framework :: Plone
Classifier: Programming Language :: Python
